confipy/__init__.py
confipy/converter.py
confipy/notation.py
confipy/parser.py
confipy/reader.py
confipy-0.0.2.dist-info/DESCRIPTION.rst
confipy-0.0.2.dist-info/METADATA
confipy-0.0.2.dist-info/RECORD
confipy-0.0.2.dist-info/WHEEL
confipy-0.0.2.dist-info/metadata.json
confipy-0.0.2.dist-info/top_level.txt
